{
  "$schema": "http://json-schema.org/draft-07/schema#",
  "title": "Value",
  "type": "object",
  "required": [
    "coin"
  ],
  "properties": {
    "coin": {
      "type": "string"
    },
    "multiasset": {
      "anyOf": [
        {
          "$ref": "#/definitions/MultiAsset"
        },
        {
          "type": "null"
        }
      ]
    }
  },
  "definitions": {
    "Assets": {
      "type": "object",
      "additionalProperties": {
        "type": "string"
      }
    },
    "MultiAsset": {
      "type": "object",
      "additionalProperties": {
        "$ref": "#/definitions/Assets"
      }
    }
  }
}